{
  "seminars": [
    {
      "id": "5",
      "title": "Семинар по Redux",
      "date": "2024-05-20",
      "description": "Менеджмент состояния в React-приложениях. Рассмотрим основные концепции Redux, работу с actions, reducers, middleware и библиотекой Redux Toolkit."
    },
    {
      "id": "7",
      "title": "Создание REST API",
      "date": "2024-06-10",
      "description": "Как правильно проектировать REST API. Узнаем о принципах REST, методах HTTP, аутентификации, документации API и обработке ошибок."
    },
    {
      "id": "8",
      "title": "Next.js для начинающих",
      "date": "2024-06-15",
      "description": "Основы работы с Next.js. Разберем SSR, SSG, ISR, роутинг, работу с API-роутами и стилизацию в Next.js."
    },
    {
      "id": "9",
      "title": "React Query",
      "date": "2024-06-20",
      "description": "Как оптимизировать работу с данными в React. Познакомимся с React Query, кешированием данных, синхронизацией и управлением состоянием сервера."
    },
    {
      "id": "10",
      "title": "Tailwind CSS",
      "date": "2024-06-25",
      "description": "Как быстро стилизовать приложения с Tailwind. Разберем utility-first подход, кастомизацию тем и создание адаптивного дизайна."
    },
    {
      "id": "11",
      "title": "Vue.js vs React",
      "date": "2024-07-01",
      "description": "Сравнение популярных фреймворков. Рассмотрим основные различия в архитектуре, производительности, удобстве разработки и экосистемах Vue.js и React."
    },
    {
      "id": "12",
      "title": "Тестирование в React",
      "date": "2024-07-05",
      "description": "Использование Jest и React Testing Library. Узнаем о юнит-тестировании, моках, снапшотах и лучших практиках тестирования React-компонентов."
    },
    {
      "id": "13",
      "title": "Docker и контейнеризация",
      "date": "2024-07-10",
      "description": "Как запускать приложения в Docker. Познакомимся с контейнерами, образами, Docker Compose и основами DevOps-процессов."
    },
    {
      "id": "14",
      "title": "Работа с WebSockets",
      "date": "2024-07-15",
      "description": "Реализация реального времени в веб-приложениях. Разберем WebSockets, их отличие от HTTP, примеры использования в чатах и других сервисах."
    },
    {
      "id": "15",
      "title": "Аутентификация в React",
      "date": "2024-07-20",
      "description": "JWT, OAuth и другие способы аутентификации. Узнаем, как безопасно реализовать вход в приложение и управление сессиями пользователей."
    },
    {
      "id": "16",
      "title": "Оптимизация производительности React-приложений",
      "date": "2024-07-25",
      "description": "Использование мемоизации и профилирования. Разберем React.memo, useMemo, useCallback, lazy loading и другие техники оптимизации."
    },
    {
      "id": "17",
      "title": "Разработка Progressive Web Apps (PWA)",
      "date": "2024-08-01",
      "description": "Создание офлайн-приложений с PWA. Рассмотрим service workers, кеширование ресурсов, уведомления и улучшение UX."
    }
  ]
}